README.rst
setup.cfg
setup.py
pypicount/__init__.py
pypicount/counter.py
pypicount/test_main.py
pypicount.egg-info/PKG-INFO
pypicount.egg-info/SOURCES.txt
pypicount.egg-info/dependency_links.txt
pypicount.egg-info/entry_points.txt
pypicount.egg-info/not-zip-safe
pypicount.egg-info/top_level.txt