Metadata-Version: 1.1
Name: pypicount
Version: 0.0dev
Summary: Count download pypi packages
Home-page: http://github.com/cleder/pypicount
Author: Christian Ledermann
Author-email: christian.ledermann@gmail.com
License: GPL
Keywords: pypi cheeseshop
Platform: UNKNOWN
Classifier: Programming Language :: Python
Classifier: Programming Language :: Python :: 2
Classifier: Programming Language :: Python :: 2.7
Classifier: Programming Language :: Python :: 3
Classifier: Programming Language :: Python :: 3.4
Classifier: Intended Audience :: Developers
Classifier: License :: OSI Approved :: GNU Library or Lesser General Public License (LGPL)
Classifier: Development Status :: 4 - Beta
Classifier: Operating System :: OS Independent
